{"openapi":"3.1.0","info":{"title":"FastAPI","version":"0.1.0"},"paths":{"/notes/":{"get":{"summary":"Get Notes","operationId":"get_notes_notes__get","responses":{"200":{"description":"Successful Response","content":{"application/json":{"schema":{"items":{"$ref":"#/components/schemas/Note"},"type":"array","title":"Response Get Notes Notes  Get"}}}}}}},"/note/":{"post":{"summary":"Create Note","operationId":"create_note_note__post","requestBody":{"content":{"application/json":{"schema":{"$ref":"#/components/schemas/Note"}}},"required":true},"responses":{"200":{"description":"Successful Response","content":{"application/json":{"schema":{}}}},"422":{"description":"Validation Error","content":{"application/json":{"schema":{"$ref":"#/components/schemas/HTTPValidationError"}}}}}}}},"components":{"schemas":{"HTTPValidationError":{"properties":{"detail":{"items":{"$ref":"#/components/schemas/ValidationError"},"type":"array","title":"Detail"}},"type":"object","title":"HTTPValidationError"},"Note":{"properties":{"id":{"type":"integer","title":"Id"},"title":{"type":"string","title":"Title"},"file_name":{"type":"string","title":"File Name"},"created_at":{"type":"string","title":"Created At"},"updated_at":{"type":"string","title":"Updated At"}},"type":"object","required":["title","file_name","created_at","updated_at"],"title":"Note"},"ValidationError":{"properties":{"loc":{"items":{"anyOf":[{"type":"string"},{"type":"integer"}]},"type":"array","title":"Location"},"msg":{"type":"string","title":"Message"},"type":{"type":"string","title":"Error Type"}},"type":"object","required":["loc","msg","type"],"title":"ValidationError"}}}}